PathMePy_Gustoon
