Metadata-Version: 2.1
Name: PathMePy-Gustoon
Version: 0.3.1
Summary: A tool to add scripts to Path
Author: Gustoon
Author-email: 
Classifier: Programming Language :: Python :: 3
Classifier: License :: OSI Approved :: MIT License
Classifier: Operating System :: OS Independent
Requires-Python: >=3.2
License-File: LICENSE.txt
